rev_HunYuan/__init__.py
rev_HunYuan/chat.py
rev_hunyuan-0.22.dist-info/LICENSE
rev_hunyuan-0.22.dist-info/METADATA
rev_hunyuan-0.22.dist-info/WHEEL
rev_hunyuan-0.22.dist-info/top_level.txt
rev_hunyuan-0.22.dist-info/RECORD
