Metadata-Version: 2.1
Name: rev-hunyuan
Version: 0.22
Summary: 通过cookie信息快速访问腾讯混元
Home-page: https://github.com/HarcicYang/rev_HunYuan
Author: Harcic
Author-email: harcic@outlook.com
License-File: LICENSE
